timetables/base/__init__.py
timetables/base/model.py
timetables/parser/base/__init__.py
timetables/parser/base/dataset.py
timetables/parser/base/file.py
timetables/parser/base/parser.py
timetables/schemas/__init__.py
timetables/schemas/classroom.py
timetables/schemas/lesson.py
timetables/schemas/register.py
timetables/schemas/subject.py
timetables/schemas/teacher.py
timetables/schemas/team.py
timetables/schemas/url.py
timetables/schemas/weekday.py
timetables_lib-1.0.0.dist-info/WHEEL
timetables_lib-1.0.0.dist-info/METADATA
timetables_lib-1.0.0.dist-info/RECORD
